cotopaxi
