Metadata-Version: 2.1
Name: cotopaxi
Version: 1.5.2
Summary: Set of tools for security testing of Internet of Things devices using specific network protocols.
Home-page: https://github.com/Samsung/cotopaxi
Author: Jakub Botwicz
Author-email: cotopaxi.tool@protonmail.com
License: GPLv2
Project-URL: Bug Reports, https://github.com/Samsung/cotopaxi/issues
Project-URL: Source Code, https://github.com/Samsung/cotopaxi
Keywords: IoT,security,network,protocols,fuzzing,fingerprinting,vulnerabilities,AMQP,CoAP,DTLS,HTCPCP,KNX,mDNS,MQTT,MQTT-SN,QUIC,RTSP,SSDP
Platform: UNKNOWN
Classifier: Development Status :: 5 - Production/Stable
Classifier: Environment :: Console
Classifier: Intended Audience :: Developers
Classifier: Intended Audience :: Information Technology
Classifier: Intended Audience :: Science/Research
Classifier: Intended Audience :: System Administrators
Classifier: Intended Audience :: Telecommunications Industry
Classifier: Programming Language :: Python :: 2
Classifier: Programming Language :: Python :: 2.7
Classifier: Programming Language :: Python :: 3
Classifier: Programming Language :: Python :: 3.6
Classifier: Programming Language :: Python :: 3.7
Classifier: Programming Language :: Python :: 3.8
Classifier: License :: OSI Approved :: GNU General Public License v2 (GPLv2)
Classifier: Operating System :: OS Independent
Classifier: Topic :: Internet
Classifier: Topic :: Scientific/Engineering
Classifier: Topic :: Security
Classifier: Topic :: Software Development
Classifier: Topic :: Software Development :: Testing
Classifier: Topic :: System
Classifier: Topic :: System :: Networking
Requires-Python: >=2.7, !=3.0.*, !=3.1.*, !=3.2.*, !=3.3.*, !=3.4.*, !=3.5.*, !=3.9.*, <4
Requires-Dist: dnslib (>=0.9.7)
Requires-Dist: hexdump (>=3.3)
Requires-Dist: IPy (>=0.83)
Requires-Dist: pycryptodomex
Requires-Dist: PyYAML (>=3.12)
Requires-Dist: scapy (>=2.4.3)
Requires-Dist: enum34 ; python_version < "3.0.0"
Requires-Dist: validators (==0.16) ; python_version < "3.0.0"
Requires-Dist: validators ; python_version < "4.0.0"
Provides-Extra: all
Requires-Dist: configparser ; extra == 'all'
Requires-Dist: coverage ; extra == 'all'
Requires-Dist: pre-commit ; extra == 'all'
Requires-Dist: pydocstyle ; extra == 'all'
Requires-Dist: pylint ; extra == 'all'
Requires-Dist: pytest ; extra == 'all'
Requires-Dist: timeout-decorator ; extra == 'all'
Requires-Dist: bandit ; (python_version > "3.0.0") and extra == 'all'
Requires-Dist: black ; (python_version > "3.0.0") and extra == 'all'
Requires-Dist: pandas (>=1.0.5) ; (python_version > "3.0.0") and extra == 'all'
Requires-Dist: sklearn ; (python_version > "3.0.0") and extra == 'all'
Requires-Dist: tensorflow (>=2.2.0) ; (python_version > "3.0.0") and extra == 'all'
Requires-Dist: xgboost ; (python_version > "3.0.0") and extra == 'all'
Provides-Extra: dev
Requires-Dist: configparser ; extra == 'dev'
Requires-Dist: coverage ; extra == 'dev'
Requires-Dist: pre-commit ; extra == 'dev'
Requires-Dist: pydocstyle ; extra == 'dev'
Requires-Dist: pylint ; extra == 'dev'
Requires-Dist: pytest ; extra == 'dev'
Requires-Dist: timeout-decorator ; extra == 'dev'
Requires-Dist: bandit ; (python_version > "3.0.0") and extra == 'dev'
Requires-Dist: black ; (python_version > "3.0.0") and extra == 'dev'
Provides-Extra: ml
Requires-Dist: pandas (>=1.0.5) ; (python_version > "3.0.0") and extra == 'ml'
Requires-Dist: sklearn ; (python_version > "3.0.0") and extra == 'ml'
Requires-Dist: tensorflow (>=2.2.0) ; (python_version > "3.0.0") and extra == 'ml'
Requires-Dist: xgboost ; (python_version > "3.0.0") and extra == 'ml'
